accelasc/__init__.py
accelasc/accel_asc.py
accelasc-1.0.4.dist-info/LICENSE
accelasc-1.0.4.dist-info/METADATA
accelasc-1.0.4.dist-info/WHEEL
accelasc-1.0.4.dist-info/top_level.txt
accelasc-1.0.4.dist-info/RECORD
