Metadata-Version: 2.1
Name: accelasc
Version: 1.0.4
Summary: implementation of accel_asc algorithm for integer partitions
Home-page: https://github.com/anthony-aylward/accelasc
Author: Anthony Aylward
Author-email: aaylward@salk.edu
License: UNKNOWN
Platform: UNKNOWN
Classifier: Programming Language :: Python :: 3
Classifier: License :: OSI Approved :: MIT License
Classifier: Operating System :: OS Independent
License-File: LICENSE
